odoo/addons/purchase_invoice_status_line/README.rst
odoo/addons/purchase_invoice_status_line/__init__.py
odoo/addons/purchase_invoice_status_line/__manifest__.py
odoo/addons/purchase_invoice_status_line/hooks.py
odoo/addons/purchase_invoice_status_line/i18n/it.po
odoo/addons/purchase_invoice_status_line/i18n/purchase_invoice_status_line.pot
odoo/addons/purchase_invoice_status_line/models/__init__.py
odoo/addons/purchase_invoice_status_line/models/purchase_order.py
odoo/addons/purchase_invoice_status_line/models/purchase_order_line.py
odoo/addons/purchase_invoice_status_line/readme/CONTRIBUTORS.md
odoo/addons/purchase_invoice_status_line/readme/DESCRIPTION.md
odoo/addons/purchase_invoice_status_line/readme/USAGE.md
odoo/addons/purchase_invoice_status_line/static/description/icon.png
odoo/addons/purchase_invoice_status_line/static/description/index.html
odoo/addons/purchase_invoice_status_line/tests/__init__.py
odoo/addons/purchase_invoice_status_line/tests/test_purchase_invoice_status_line.py
odoo/addons/purchase_invoice_status_line/views/purchase_order_line_views.xml
odoo_addon_purchase_invoice_status_line-18.0.1.0.1.dist-info/METADATA
odoo_addon_purchase_invoice_status_line-18.0.1.0.1.dist-info/WHEEL
odoo_addon_purchase_invoice_status_line-18.0.1.0.1.dist-info/top_level.txt
odoo_addon_purchase_invoice_status_line-18.0.1.0.1.dist-info/RECORD
